LICENSE.rst
MANIFEST.in
README.rst
setup.py
varstar/__init__.py
varstar/light_curve_plots.py
varstar/sinusoid.py
varstar/sinusoid_api.py
varstar/test_sinusoid.py
varstar/version.py
varstar.egg-info/PKG-INFO
varstar.egg-info/SOURCES.txt
varstar.egg-info/dependency_links.txt
varstar.egg-info/requires.txt
varstar.egg-info/top_level.txt