Metadata-Version: 1.1
Name: varstar
Version: 0.1.0
Summary: Utilities for analyzing variable star data
Home-page: http://github.com/mwcraig/varstar
Author: Matt Craig
Author-email: mcraig@mnstate.edu
License: BSD 3-clause
Platform: UNKNOWN
Classifier: Development Status :: 3 - Alpha
Classifier: License :: OSI Approved :: BSD License
Classifier: Programming Language :: Python :: 2.7
Classifier: Programming Language :: Python :: 3
Classifier: Intended Audience :: Science/Research
Classifier: Topic :: Scientific/Engineering :: Astronomy
